{
   "source" : "lists.cpan.org",
   "rssfeed" : "http://nntp.x.perl.org/rss/perl.macperl.toolbox.rdf",
   "archive" : "http://www.mail-archive.com/macperl-toolbox@perl.org/ [after 2001-01] http://bumppo.net/lists/macperl-toolbox/",
   "nntp" : "http://nntp.perl.org/group/perl.macperl.toolbox",
   "name" : "macperl-toolbox",
   "date_last_confirmed_active" : null,
   "comments" : "",
   "keywords" : "",
   "unsub" : " Send an empty email to mailto: macperl-toolbox-unsubscribe@perl.org",
   "summary" : "Discussion of MacPerl modules handling the Mac OS APIs.",
   "sub" : " Send an empty email to mailto: macperl-toolbox-subscribe@perl.org",
   "help" : " send an empty email to mailto: macperl-toolbox-help@perl.org",
   "url" : "http://www.macperl.com/depts/mlist.html",
   "category" : "Mac Ports",
   "id" : "177",
   "address" : "",
   "defunct" : "0",
   "module" : ""
}