{
   "source" : "lists.cpan.org",
   "rssfeed" : null,
   "archive" : "http://www.webmin.com/webmin/mailing.html",
   "nntp" : null,
   "name" : "webmin-l",
   "date_last_confirmed_active" : null,
   "comments" : "",
   "keywords" : "",
   "unsub" : "  http://www.webmin.com/webmin/mailing.html",
   "summary" : "The list exists to discuss Webmin and to announce new versions. ",
   "sub" : "  http://www.webmin.com/webmin/mailing.html",
   "help" : null,
   "url" : "http://www.webmin.com/webmin/",
   "category" : "Sysadmin",
   "id" : "259",
   "address" : "",
   "defunct" : "0",
   "module" : ""
}